mastercard_spendcontrols-1.0.4.dist-info/DESCRIPTION.rst
mastercard_spendcontrols-1.0.4.dist-info/METADATA
mastercard_spendcontrols-1.0.4.dist-info/RECORD
mastercard_spendcontrols-1.0.4.dist-info/WHEEL
mastercard_spendcontrols-1.0.4.dist-info/metadata.json
mastercard_spendcontrols-1.0.4.dist-info/top_level.txt
mastercardspendcontrols/__init__.py
mastercardspendcontrols/alertall.py
mastercardspendcontrols/alerts.py
mastercardspendcontrols/amount.py
mastercardspendcontrols/amountdecline.py
mastercardspendcontrols/batch.py
mastercardspendcontrols/budgetalert.py
mastercardspendcontrols/budgetalertwithbudgetid.py
mastercardspendcontrols/budgetdecline.py
mastercardspendcontrols/budgetdeclinewithbudgetid.py
mastercardspendcontrols/card.py
mastercardspendcontrols/channel.py
mastercardspendcontrols/channeldecline.py
mastercardspendcontrols/combinationctrlsalertresource.py
mastercardspendcontrols/combinationctrlsalertresourcefilterid.py
mastercardspendcontrols/combinationctrlsdeclineresource.py
mastercardspendcontrols/combinationctrlsdeclineresourcefilterid.py
mastercardspendcontrols/combinationctrlsdeclinesresource.py
mastercardspendcontrols/controls.py
mastercardspendcontrols/controlshistory.py
mastercardspendcontrols/crossborder.py
mastercardspendcontrols/crossborderdecline.py
mastercardspendcontrols/declineall.py
mastercardspendcontrols/declines.py
mastercardspendcontrols/geolocationalert.py
mastercardspendcontrols/geolocationdecline.py
mastercardspendcontrols/merchantcategorycodealert.py
mastercardspendcontrols/merchantcategorycodedecline.py
mastercardspendcontrols/notification.py
mastercardspendcontrols/resourceconfig.py
mastercardspendcontrols/travelmarkeralert.py
mastercardspendcontrols/travelmarkeralertwithtravelid.py
mastercardspendcontrols/travelmarkerdecline.py
mastercardspendcontrols/travelmarkerdeclinewithtravelid.py
mastercardspendcontrols/txnhistory.py
mastercardspendcontrols/verify.py
